mlflow/__init__.py
mlflow/__main__.py
mlflow/_doctor.py
mlflow/_spark_autologging.py
mlflow/catboost.py
mlflow/cli.py
mlflow/client.py
mlflow/db.py
mlflow/diviner.py
mlflow/environment_variables.py
mlflow/exceptions.py
mlflow/experiments.py
mlflow/h2o.py
mlflow/johnsnowlabs.py
mlflow/keras.py
mlflow/lightgbm.py
mlflow/llm.py
mlflow/ml_package_versions.py
mlflow/mleap.py
mlflow/onnx.py
mlflow/pmdarima.py
mlflow/prophet.py
mlflow/pypi_package_index.json
mlflow/runs.py
mlflow/shap.py
mlflow/spacy.py
mlflow/spark.py
mlflow/statsmodels.py
mlflow/transformers.py
mlflow/version.py
mlflow/artifacts/__init__.py
mlflow/azure/__init__.py
mlflow/azure/client.py
mlflow/deployments/__init__.py
mlflow/deployments/base.py
mlflow/deployments/cli.py
mlflow/deployments/interface.py
mlflow/deployments/plugin_manager.py
mlflow/deployments/utils.py
mlflow/entities/__init__.py
mlflow/entities/_mlflow_object.py
mlflow/entities/experiment.py
mlflow/entities/experiment_tag.py
mlflow/entities/file_info.py
mlflow/entities/lifecycle_stage.py
mlflow/entities/metric.py
mlflow/entities/param.py
mlflow/entities/run.py
mlflow/entities/run_data.py
mlflow/entities/run_info.py
mlflow/entities/run_status.py
mlflow/entities/run_tag.py
mlflow/entities/source_type.py
mlflow/entities/view_type.py
mlflow/entities/model_registry/__init__.py
mlflow/entities/model_registry/_model_registry_entity.py
mlflow/entities/model_registry/model_version.py
mlflow/entities/model_registry/model_version_stages.py
mlflow/entities/model_registry/model_version_status.py
mlflow/entities/model_registry/model_version_tag.py
mlflow/entities/model_registry/registered_model.py
mlflow/entities/model_registry/registered_model_alias.py
mlflow/entities/model_registry/registered_model_tag.py
mlflow/fastai/__init__.py
mlflow/fastai/callback.py
mlflow/gluon/__init__.py
mlflow/gluon/_autolog.py
mlflow/langchain/__init__.py
mlflow/langchain/api_request_parallel_processor.py
mlflow/models/__init__.py
mlflow/models/cli.py
mlflow_tmp-2.2.26.dist-info/LICENSE.txt
mlflow_tmp-2.2.26.dist-info/METADATA
mlflow_tmp-2.2.26.dist-info/WHEEL
mlflow_tmp-2.2.26.dist-info/entry_points.txt
mlflow_tmp-2.2.26.dist-info/top_level.txt
mlflow_tmp-2.2.26.dist-info/RECORD
